TcEncoder
